{"chunk_definitions":[{"row":22,"row_count":1,"visible":true,"expansion_state":0,"options":{"engine":"r","label":"setup","include":false,"dev":"png"},"document_id":"A4119C86","chunk_id":"csetup_chunk","chunk_label":"setup"},{"row":44,"row_count":1,"visible":true,"expansion_state":0,"options":{"engine":"r","echo":false,"label":"unnamed-chunk-2","dev":"png"},"document_id":"A4119C86","chunk_id":"c4wo1rldgn7b4","chunk_label":"unnamed-chunk-3"},{"row":124,"row_count":1,"visible":true,"expansion_state":0,"options":{"engine":"r","echo":true,"label":"unnamed-chunk-3","dev":"png"},"document_id":"A4119C86","chunk_id":"cbkhurwvu56th","chunk_label":"unnamed-chunk-5"},{"row":135,"row_count":1,"visible":true,"expansion_state":0,"options":{"engine":"r","echo":false,"label":"unnamed-chunk-7","dev":"png"},"document_id":"A4119C86","chunk_id":"cmmja6ii3cql5","chunk_label":"unnamed-chunk-6"},{"row":144,"row_count":1,"visible":true,"expansion_state":0,"options":{"engine":"r","echo":false,"label":"unnamed-chunk-9","dev":"png"},"document_id":"A4119C86","chunk_id":"c1trf04xpx04g","chunk_label":"unnamed-chunk-7"}],"doc_write_time":1721545760,"working_dir":null,"default_chunk_options":{"echo":true}}